pystray/__init__.py
pystray/_appindicator.py
pystray/_base.py
pystray/_darwin.py
pystray/_dummy.py
pystray/_gtk.py
pystray/_info.py
pystray/_win32.py
pystray/_xorg.py
pystray/_util/__init__.py
pystray/_util/gtk.py
pystray/_util/notify_dbus.py
pystray/_util/win32.py
pystray-0.19.4.dist-info/COPYING
pystray-0.19.4.dist-info/COPYING.LGPL
pystray-0.19.4.dist-info/METADATA
pystray-0.19.4.dist-info/WHEEL
pystray-0.19.4.dist-info/top_level.txt
pystray-0.19.4.dist-info/zip-safe
pystray-0.19.4.dist-info/RECORD
