Metadata-Version: 2.1
Name: pystray
Version: 0.19.4
Summary: Provides systray integration
Home-page: https://github.com/moses-palmer/pystray
Author: Moses Palmér
Author-email: moses.palmer@gmail.com
License: LGPLv3
Keywords: system tray icon,systray icon
Platform: UNKNOWN
Classifier: Development Status :: 4 - Beta
Classifier: Intended Audience :: Developers
Classifier: License :: OSI Approved :: GNU Lesser General Public License v3 (LGPLv3)
Classifier: Operating System :: MacOS :: MacOS X
Classifier: Operating System :: Microsoft :: Windows :: Windows NT/2000
Classifier: Operating System :: POSIX
Classifier: Programming Language :: Python
Classifier: Programming Language :: Python :: 2.7
Classifier: Programming Language :: Python :: 3.4
License-File: COPYING
License-File: COPYING.LGPL
